Metadata-Version: 2.1
Name: multi-agent-decision
Version: 0.3
Summary: Simulates the actions which agents take under multi-agent systems and social networks
Home-page: https://github.com/ankur-tutlani/multi-agent-decision
Download-URL: https://github.com/ankur-tutlani/multi_agent_decision/archive/refs/tags/v_03.tar.gz
Author: ankurtutlani
Author-email: ankur.tutlani@gmail.com
License: MIT
Keywords: game theory,evolutionary game,social norms,multi-agent systems,evolution,social network,computational economics,simulation,agent-based modeling,computation
Classifier: Development Status :: 3 - Alpha
Classifier: Intended Audience :: Developers
Classifier: Topic :: Software Development :: Build Tools
Classifier: License :: OSI Approved :: MIT License
Classifier: Programming Language :: Python :: 3.11
License-File: LICENSE.txt
